pygeoconv/__init__.py
pygeoconv/_esri_json.py
pygeoconv/_geojson.py
pygeoconv/_wkt.py
pygeoconv/_wkt_parser.py
pygeoconv/errors.py
pygeoconv/pygeoconv.py
pygeoconv/ply/__init__.py
pygeoconv/ply/lex.py
pygeoconv/ply/yacc.py
pygeoconv-1.0.1.dist-info/LICENSE
pygeoconv-1.0.1.dist-info/METADATA
pygeoconv-1.0.1.dist-info/WHEEL
pygeoconv-1.0.1.dist-info/top_level.txt
pygeoconv-1.0.1.dist-info/RECORD
