Metadata-Version: 2.1
Name: pygeoconv
Version: 1.0.1
Summary: Python tool for converting geometries between WKT, GeoJson and Esri Json formats
Home-page: https://github.com/anton-lundkvist/py-geo-conv
Author: Anton Lundkvist
Author-email: antonlundkvist@gmail.com
License: MIT
Classifier: Programming Language :: Python :: 3
Classifier: License :: OSI Approved :: MIT License
Classifier: Operating System :: OS Independent
Requires-Python: >=3.6
License-File: LICENSE
